playwright_self_healing/__init__.py
playwright_self_healing/cache.py
playwright_self_healing/claude_finder.py
playwright_self_healing/config.py
playwright_self_healing/locator_wrapper.py
playwright_self_healing/page_wrapper.py
playwright_self_healing/rate_limiter.py
playwright_self_healing/screenshot_cache.py
playwright_self_healing/version.py
playwright_self_healing/visual_feedback.py
playwright_self_healing-0.2.0.dist-info/licenses/LICENSE
tests/__init__.py
tests/conftest.py
tests/test_cache.py
tests/test_config.py
tests/test_rate_limiter.py
playwright_self_healing-0.2.0.dist-info/METADATA
playwright_self_healing-0.2.0.dist-info/WHEEL
playwright_self_healing-0.2.0.dist-info/top_level.txt
playwright_self_healing-0.2.0.dist-info/RECORD
