Metadata-Version: 2.4
Name: playwright-self-healing
Version: 0.2.0
Summary: AI-powered self-healing locators for Playwright Python tests
Author-email: Diego Bermudez <bermudezdiegoalejandro@gmail.com>
License: MIT
Project-URL: Homepage, https://github.com/saalejo/playwright-self-healing
Project-URL: Documentation, https://github.com/saalejo/playwright-self-healing/blob/main/README.md
Project-URL: Repository, https://github.com/saalejo/playwright-self-healing
Project-URL: Issues, https://github.com/saalejo/playwright-self-healing/issues
Keywords: playwright,testing,ai,self-healing,locators,automation,claude,anthropic
Classifier: Development Status :: 3 - Alpha
Classifier: Intended Audience :: Developers
Classifier: License :: OSI Approved :: MIT License
Classifier: Programming Language :: Python :: 3
Classifier: Programming Language :: Python :: 3.8
Classifier: Programming Language :: Python :: 3.9
Classifier: Programming Language :: Python :: 3.10
Classifier: Programming Language :: Python :: 3.11
Classifier: Programming Language :: Python :: 3.12
Classifier: Programming Language :: Python :: 3.13
Classifier: Topic :: Software Development :: Testing
Classifier: Topic :: Software Development :: Quality Assurance
Requires-Python: >=3.8.1
License-File: LICENSE
Requires-Dist: playwright>=1.40.0
Requires-Dist: anthropic>=0.40.0
Requires-Dist: pyyaml>=6.0
Requires-Dist: pillow>=10.0.0
Requires-Dist: twine>=6.1.0
Provides-Extra: dev
Requires-Dist: pytest>=7.0.0; extra == "dev"
Requires-Dist: pytest-playwright>=0.4.0; extra == "dev"
Requires-Dist: pytest-mock>=3.10.0; extra == "dev"
Requires-Dist: black>=23.0.0; extra == "dev"
Requires-Dist: flake8>=6.0.0; extra == "dev"
Requires-Dist: mypy>=1.0.0; extra == "dev"
Dynamic: license-file
